precice_config_visualizer_gui-1.0.0.data/data/share/applications/org.precice.config_visualizer.desktop
precice_config_visualizer_gui-1.0.0.data/data/share/icons/hicolor/scalable/apps/org.precice.config_visualizer.svg
precice_config_visualizer_gui-1.0.0.data/data/share/metainfo/org.precice.config_visualizer.metainfo.xml
precice_config_visualizer_gui-1.0.0.dist-info/licenses/LICENSE
preciceconfigvisualizer/gui/__init__.py
preciceconfigvisualizer/gui/gui.py
preciceconfigvisualizer/gui/window.py
precice_config_visualizer_gui-1.0.0.dist-info/METADATA
precice_config_visualizer_gui-1.0.0.dist-info/WHEEL
precice_config_visualizer_gui-1.0.0.dist-info/entry_points.txt
precice_config_visualizer_gui-1.0.0.dist-info/top_level.txt
precice_config_visualizer_gui-1.0.0.dist-info/RECORD
