Metadata-Version: 2.4
Name: precice-config-visualizer-gui
Version: 1.0.0
Summary: A GUI tool for visualizing a preCICE configuration file as a dot file.
Author-email: The preCICE Developers <info@precice.org>
Maintainer-email: Frédéric Simonis <frederic.simonis@ipvs.uni-stuttgart.de>
License-Expression: MIT
Project-URL: Homepage, https://precice.org
Project-URL: Documentation, https://precice.org/tooling-config-visualization.html
Project-URL: Repository, https://github.com/precice/config-visualizer-gui.git
Project-URL: Bug Tracker, https://github.com/precice/config-visualizer-gui/issues
Keywords: preCICE,dot,graphviz,XML,interactive,configuration,visualization
Classifier: Development Status :: 4 - Beta
Classifier: Programming Language :: Python :: 3 :: Only
Classifier: Programming Language :: Python :: 3.8
Classifier: Topic :: Scientific/Engineering :: Visualization
Classifier: Topic :: Utilities
Requires-Python: >=3.8
License-File: LICENSE
Requires-Dist: xdot
Requires-Dist: PyGObject
Requires-Dist: precice-config-visualizer>=1
Dynamic: license-file
